<?xml version="1.0" encoding="utf-8" ?>
<dwsync>
<file name="autocomplete.js" server="qxu2149940242.my3w.com" local="131653023000277877" remote="131652239400000000" Dst="0" />
<file name="autocomplete.min.js" server="qxu2149940242.my3w.com" local="131653023003518062" remote="131652239400000000" Dst="0" />
<file name="cover.js" server="qxu2149940242.my3w.com" local="131653023006808251" remote="131652239400000000" Dst="0" />
<file name="cover.min.js" server="qxu2149940242.my3w.com" local="131653023009848425" remote="131652239400000000" Dst="0" />
<file name="datepicker.js" server="qxu2149940242.my3w.com" local="131653023013168614" remote="131652239400000000" Dst="0" />
<file name="datepicker.min.js" server="qxu2149940242.my3w.com" local="131653023016308794" remote="131652239400000000" Dst="0" />
<file name="form-password.js" server="qxu2149940242.my3w.com" local="131653023019468975" remote="131652239400000000" Dst="0" />
<file name="form-password.min.js" server="qxu2149940242.my3w.com" local="131653023022799165" remote="131652239400000000" Dst="0" />
<file name="form-select.js" server="qxu2149940242.my3w.com" local="131653023026119355" remote="131652239400000000" Dst="0" />
<file name="form-select.min.js" server="qxu2149940242.my3w.com" local="131653023029059523" remote="131652239400000000" Dst="0" />
<file name="htmleditor.js" server="qxu2149940242.my3w.com" local="131653023032529722" remote="131652239400000000" Dst="0" />
<file name="htmleditor.min.js" server="qxu2149940242.my3w.com" local="131653023035489891" remote="131652239400000000" Dst="0" />
<file name="nestable.js" server="qxu2149940242.my3w.com" local="131653023038610070" remote="131652239400000000" Dst="0" />
<file name="nestable.min.js" server="qxu2149940242.my3w.com" local="131653023053110899" remote="131652239400000000" Dst="0" />
<file name="notify.js" server="qxu2149940242.my3w.com" local="131653023056501093" remote="131652239400000000" Dst="0" />
<file name="notify.min.js" server="qxu2149940242.my3w.com" local="131653023059931289" remote="131652239400000000" Dst="0" />
<file name="pagination.js" server="qxu2149940242.my3w.com" local="131653023062931461" remote="131652239400000000" Dst="0" />
<file name="pagination.min.js" server="qxu2149940242.my3w.com" local="131653023100753624" remote="131652239400000000" Dst="0" />
<file name="search.js" server="qxu2149940242.my3w.com" local="131653023104043812" remote="131652239400000000" Dst="0" />
<file name="search.min.js" server="qxu2149940242.my3w.com" local="131653023107724023" remote="131652239400000000" Dst="0" />
<file name="sortable.js" server="qxu2149940242.my3w.com" local="131653023110834201" remote="131652239400000000" Dst="0" />
<file name="sortable.min.js" server="qxu2149940242.my3w.com" local="131653023154406693" remote="131652239400000000" Dst="0" />
<file name="sticky.js" server="qxu2149940242.my3w.com" local="131653023157616876" remote="131652239400000000" Dst="0" />
<file name="sticky.min.js" server="qxu2149940242.my3w.com" local="131653023160927066" remote="131652239400000000" Dst="0" />
<file name="timepicker.js" server="qxu2149940242.my3w.com" local="131653023164277257" remote="131652239400000000" Dst="0" />
<file name="timepicker.min.js" server="qxu2149940242.my3w.com" local="131653023167347433" remote="131652239400000000" Dst="0" />
<file name="upload.js" server="qxu2149940242.my3w.com" local="131653023170687624" remote="131652239400000000" Dst="0" />
<file name="upload.min.js" server="qxu2149940242.my3w.com" local="131653023174277829" remote="131652239400000000" Dst="0" />
</dwsync>